Workbook

Sheet Commandes
A1: Date | B1: N° commande | C1: Produit | D1: Pays | E1: Reçu du client (€) | F1: Fournisseur payé (€) | G1: Frais Shopify (€) | H1: URSSAF (€) | I1: Impôt libératoire (€) | J1: Total payé (€) | K1: Bénéfice (€) | L1: Mois | M1: Remarque
A2: 46321 | B2: #1003 | C2: Distributeur eau et croquettes (gris) | D2: France | E2: 29.99 | F2: 18.4 | G2: 0.7 | H2: =IF(E2="","",ROUND(E2*Réglages!$B$3,2)) -> 3.69 | I2: =IF(E2="","",ROUND(E2*Réglages!$B$4,2)) -> 0 | J2: =IF(E2="","",F2+G2+H2+I2) -> 22.79 | K2: =IF(E2="","",E2-J2) -> 7.2 | L2: =IF(A2="","",DATE(YEAR(A2),MONTH(A2),1)) -> 46296 | M2: Fournisseur et frais estimés : à corriger avec le relevé Trade Republic et le versement Shopify
H3: =IF(E3="","",ROUND(E3*Réglages!$B$3,2)) | I3: =IF(E3="","",ROUND(E3*Réglages!$B$4,2)) | J3: =IF(E3="","",F3+G3+H3+I3) | K3: =IF(E3="","",E3-J3) | L3: =IF(A3="","",DATE(YEAR(A3),MONTH(A3),1))
H4: =IF(E4="","",ROUND(E4*Réglages!$B$3,2)) | I4: =IF(E4="","",ROUND(E4*Réglages!$B$4,2)) | J4: =IF(E4="","",F4+G4+H4+I4) | K4: =IF(E4="","",E4-J4) | L4: =IF(A4="","",DATE(YEAR(A4),MONTH(A4),1))
H5: =IF(E5="","",ROUND(E5*Réglages!$B$3,2)) | I5: =IF(E5="","",ROUND(E5*Réglages!$B$4,2)) | J5: =IF(E5="","",F5+G5+H5+I5) | K5: =IF(E5="","",E5-J5) | L5: =IF(A5="","",DATE(YEAR(A5),MONTH(A5),1))
H6: =IF(E6="","",ROUND(E6*Réglages!$B$3,2)) | I6: =IF(E6="","",ROUND(E6*Réglages!$B$4,2)) | J6: =IF(E6="","",F6+G6+H6+I6) | K6: =IF(E6="","",E6-J6) | L6: =IF(A6="","",DATE(YEAR(A6),MONTH(A6),1))
H7: =IF(E7="","",ROUND(E7*Réglages!$B$3,2)) | I7: =IF(E7="","",ROUND(E7*Réglages!$B$4,2)) | J7: =IF(E7="","",F7+G7+H7+I7) | K7: =IF(E7="","",E7-J7) | L7: =IF(A7="","",DATE(YEAR(A7),MONTH(A7),1))
H8: =IF(E8="","",ROUND(E8*Réglages!$B$3,2)) | I8: =IF(E8="","",ROUND(E8*Réglages!$B$4,2)) | J8: =IF(E8="","",F8+G8+H8+I8) | K8: =IF(E8="","",E8-J8) | L8: =IF(A8="","",DATE(YEAR(A8),MONTH(A8),1))
H9: =IF(E9="","",ROUND(E9*Réglages!$B$3,2)) | I9: =IF(E9="","",ROUND(E9*Réglages!$B$4,2)) | J9: =IF(E9="","",F9+G9+H9+I9) | K9: =IF(E9="","",E9-J9) | L9: =IF(A9="","",DATE(YEAR(A9),MONTH(A9),1))
H10: =IF(E10="","",ROUND(E10*Réglages!$B$3,2)) | I10: =IF(E10="","",ROUND(E10*Réglages!$B$4,2)) | J10: =IF(E10="","",F10+G10+H10+I10) | K10: =IF(E10="","",E10-J10) | L10: =IF(A10="","",DATE(YEAR(A10),MONTH(A10),1))
H11: =IF(E11="","",ROUND(E11*Réglages!$B$3,2)) | I11: =IF(E11="","",ROUND(E11*Réglages!$B$4,2)) | J11: =IF(E11="","",F11+G11+H11+I11) | K11: =IF(E11="","",E11-J11) | L11: =IF(A11="","",DATE(YEAR(A11),MONTH(A11),1))
H12: =IF(E12="","",ROUND(E12*Réglages!$B$3,2)) | I12: =IF(E12="","",ROUND(E12*Réglages!$B$4,2)) | J12: =IF(E12="","",F12+G12+H12+I12) | K12: =IF(E12="","",E12-J12) | L12: =IF(A12="","",DATE(YEAR(A12),MONTH(A12),1))
H13: =IF(E13="","",ROUND(E13*Réglages!$B$3,2)) | I13: =IF(E13="","",ROUND(E13*Réglages!$B$4,2)) | J13: =IF(E13="","",F13+G13+H13+I13) | K13: =IF(E13="","",E13-J13) | L13: =IF(A13="","",DATE(YEAR(A13),MONTH(A13),1))
H14: =IF(E14="","",ROUND(E14*Réglages!$B$3,2)) | I14: =IF(E14="","",ROUND(E14*Réglages!$B$4,2)) | J14: =IF(E14="","",F14+G14+H14+I14) | K14: =IF(E14="","",E14-J14) | L14: =IF(A14="","",DATE(YEAR(A14),MONTH(A14),1))
... H301: =IF(E301="","",ROUND(E301*Réglages!$B$3,2)) | I301: =IF(E301="","",ROUND(E301*Réglages!$B$4,2)) | J301: =IF(E301="","",F301+G301+H301+I301) | K301: =IF(E301="","",E301-J301) | L301: =IF(A301="","",DATE(YEAR(A301),MONTH(A301),1))

Sheet Mode d'emploi
A1: Suivi des commandes Pattoune
A3: 1. À chaque vente, ajoute UNE ligne dans l'onglet « Commandes ».
A4: 2. Tu remplis seulement les cases JAUNES (texte bleu) : date, n° de commande, produit, pays,
A5: ce que le client a payé, ce que tu as payé au fournisseur, et les frais Shopify.
A6: 3. Tout le reste se calcule tout seul : URSSAF, total payé, bénéfice, mois.
A7: 4. L'onglet « Récap par mois » te donne le chiffre d'affaires à déclarer à l'URSSAF chaque mois.
A9: Où trouver les montants :
A10: • Reçu du client : Shopify → Commandes → la commande → Total.
A11: • Fournisseur payé : ton relevé Trade Republic (montant débité par AliExpress, en euros).
A12: • Frais Shopify : Shopify → Paramètres → Paiements → Afficher les versements (ou laisse l'estimation).
A14: Réglages : vérifie le taux URSSAF dans l'onglet « Réglages » (ton espace autoentrepreneur.urssaf.fr).
A15: La pub Google n'est pas comptée ici.
... A19: Case calculée automatiquement (ne pas toucher)

Sheet Réglages
A1: Réglages
A3: Taux URSSAF (vente de marchandises) | B3: 0.123 | C3: Hypothèse : 12,3 % pour la vente de marchandises en micro-entreprise. À vérifier sur ton espace autoentrepreneur.urssaf.fr (ACRE = taux réduit la 1re année).
A4: Versement libératoire de l'impôt (0 % si tu ne l'as pas choisi) | B4: 0 | C4: Mets 1 % (0,01) seulement si tu as opté pour le versement libératoire. Sinon laisse 0.

Sheet Récap par mois
A1: Mois | B1: Nb de commandes | C1: CA à déclarer URSSAF (€) | D1: Fournisseur (€) | E1: Frais Shopify (€) | F1: URSSAF (€) | G1: Impôt libératoire (€) | H1: Bénéfice (€)
A2: 46296 | B2: =COUNTIFS(Commandes!$L$2:$L$301,A2) -> 1 | C2: =SUMIFS(Commandes!$E$2:$E$301,Commandes!$L$2:$L$301,A2) -> 29.99 | D2: =SUMIFS(Commandes!$F$2:$F$301,Commandes!$L$2:$L$301,A2) -> 18.4 | E2: =SUMIFS(Commandes!$G$2:$G$301,Commandes!$L$2:$L$301,A2) -> 0.7 | F2: =SUMIFS(Commandes!$H$2:$H$301,Commandes!$L$2:$L$301,A2) -> 3.69 | G2: =SUMIFS(Commandes!$I$2:$I$301,Commandes!$L$2:$L$301,A2) -> 0 | H2: =SUMIFS(Commandes!$K$2:$K$301,Commandes!$L$2:$L$301,A2) -> 7.2
A3: 46327 | B3: =COUNTIFS(Commandes!$L$2:$L$301,A3) -> 0 | C3: =SUMIFS(Commandes!$E$2:$E$301,Commandes!$L$2:$L$301,A3) -> 0 | D3: =SUMIFS(Commandes!$F$2:$F$301,Commandes!$L$2:$L$301,A3) -> 0 | E3: =SUMIFS(Commandes!$G$2:$G$301,Commandes!$L$2:$L$301,A3) -> 0 | F3: =SUMIFS(Commandes!$H$2:$H$301,Commandes!$L$2:$L$301,A3) -> 0 | G3: =SUMIFS(Commandes!$I$2:$I$301,Commandes!$L$2:$L$301,A3) -> 0 | H3: =SUMIFS(Commandes!$K$2:$K$301,Commandes!$L$2:$L$301,A3) -> 0
A4: 46357 | B4: =COUNTIFS(Commandes!$L$2:$L$301,A4) -> 0 | C4: =SUMIFS(Commandes!$E$2:$E$301,Commandes!$L$2:$L$301,A4) -> 0 | D4: =SUMIFS(Commandes!$F$2:$F$301,Commandes!$L$2:$L$301,A4) -> 0 | E4: =SUMIFS(Commandes!$G$2:$G$301,Commandes!$L$2:$L$301,A4) -> 0 | F4: =SUMIFS(Commandes!$H$2:$H$301,Commandes!$L$2:$L$301,A4) -> 0 | G4: =SUMIFS(Commandes!$I$2:$I$301,Commandes!$L$2:$L$301,A4) -> 0 | H4: =SUMIFS(Commandes!$K$2:$K$301,Commandes!$L$2:$L$301,A4) -> 0
A5: 46388 | B5: =COUNTIFS(Commandes!$L$2:$L$301,A5) -> 0 | C5: =SUMIFS(Commandes!$E$2:$E$301,Commandes!$L$2:$L$301,A5) -> 0 | D5: =SUMIFS(Commandes!$F$2:$F$301,Commandes!$L$2:$L$301,A5) -> 0 | E5: =SUMIFS(Commandes!$G$2:$G$301,Commandes!$L$2:$L$301,A5) -> 0 | F5: =SUMIFS(Commandes!$H$2:$H$301,Commandes!$L$2:$L$301,A5) -> 0 | G5: =SUMIFS(Commandes!$I$2:$I$301,Commandes!$L$2:$L$301,A5) -> 0 | H5: =SUMIFS(Commandes!$K$2:$K$301,Commandes!$L$2:$L$301,A5) -> 0
A6: 46419 | B6: =COUNTIFS(Commandes!$L$2:$L$301,A6) -> 0 | C6: =SUMIFS(Commandes!$E$2:$E$301,Commandes!$L$2:$L$301,A6) -> 0 | D6: =SUMIFS(Commandes!$F$2:$F$301,Commandes!$L$2:$L$301,A6) -> 0 | E6: =SUMIFS(Commandes!$G$2:$G$301,Commandes!$L$2:$L$301,A6) -> 0 | F6: =SUMIFS(Commandes!$H$2:$H$301,Commandes!$L$2:$L$301,A6) -> 0 | G6: =SUMIFS(Commandes!$I$2:$I$301,Commandes!$L$2:$L$301,A6) -> 0 | H6: =SUMIFS(Commandes!$K$2:$K$301,Commandes!$L$2:$L$301,A6) -> 0
A7: 46447 | B7: =COUNTIFS(Commandes!$L$2:$L$301,A7) -> 0 | C7: =SUMIFS(Commandes!$E$2:$E$301,Commandes!$L$2:$L$301,A7) -> 0 | D7: =SUMIFS(Commandes!$F$2:$F$301,Commandes!$L$2:$L$301,A7) -> 0 | E7: =SUMIFS(Commandes!$G$2:$G$301,Commandes!$L$2:$L$301,A7) -> 0 | F7: =SUMIFS(Commandes!$H$2:$H$301,Commandes!$L$2:$L$301,A7) -> 0 | G7: =SUMIFS(Commandes!$I$2:$I$301,Commandes!$L$2:$L$301,A7) -> 0 | H7: =SUMIFS(Commandes!$K$2:$K$301,Commandes!$L$2:$L$301,A7) -> 0
A8: 46478 | B8: =COUNTIFS(Commandes!$L$2:$L$301,A8) -> 0 | C8: =SUMIFS(Commandes!$E$2:$E$301,Commandes!$L$2:$L$301,A8) -> 0 | D8: =SUMIFS(Commandes!$F$2:$F$301,Commandes!$L$2:$L$301,A8) -> 0 | E8: =SUMIFS(Commandes!$G$2:$G$301,Commandes!$L$2:$L$301,A8) -> 0 | F8: =SUMIFS(Commandes!$H$2:$H$301,Commandes!$L$2:$L$301,A8) -> 0 | G8: =SUMIFS(Commandes!$I$2:$I$301,Commandes!$L$2:$L$301,A8) -> 0 | H8: =SUMIFS(Commandes!$K$2:$K$301,Commandes!$L$2:$L$301,A8) -> 0
A9: 46508 | B9: =COUNTIFS(Commandes!$L$2:$L$301,A9) -> 0 | C9: =SUMIFS(Commandes!$E$2:$E$301,Commandes!$L$2:$L$301,A9) -> 0 | D9: =SUMIFS(Commandes!$F$2:$F$301,Commandes!$L$2:$L$301,A9) -> 0 | E9: =SUMIFS(Commandes!$G$2:$G$301,Commandes!$L$2:$L$301,A9) -> 0 | F9: =SUMIFS(Commandes!$H$2:$H$301,Commandes!$L$2:$L$301,A9) -> 0 | G9: =SUMIFS(Commandes!$I$2:$I$301,Commandes!$L$2:$L$301,A9) -> 0 | H9: =SUMIFS(Commandes!$K$2:$K$301,Commandes!$L$2:$L$301,A9) -> 0
A10: 46539 | B10: =COUNTIFS(Commandes!$L$2:$L$301,A10) -> 0 | C10: =SUMIFS(Commandes!$E$2:$E$301,Commandes!$L$2:$L$301,A10) -> 0 | D10: =SUMIFS(Commandes!$F$2:$F$301,Commandes!$L$2:$L$301,A10) -> 0 | E10: =SUMIFS(Commandes!$G$2:$G$301,Commandes!$L$2:$L$301,A10) -> 0 | F10: =SUMIFS(Commandes!$H$2:$H$301,Commandes!$L$2:$L$301,A10) -> 0 | G10: =SUMIFS(Commandes!$I$2:$I$301,Commandes!$L$2:$L$301,A10) -> 0 | H10: =SUMIFS(Commandes!$K$2:$K$301,Commandes!$L$2:$L$301,A10) -> 0
A11: 46569 | B11: =COUNTIFS(Commandes!$L$2:$L$301,A11) -> 0 | C11: =SUMIFS(Commandes!$E$2:$E$301,Commandes!$L$2:$L$301,A11) -> 0 | D11: =SUMIFS(Commandes!$F$2:$F$301,Commandes!$L$2:$L$301,A11) -> 0 | E11: =SUMIFS(Commandes!$G$2:$G$301,Commandes!$L$2:$L$301,A11) -> 0 | F11: =SUMIFS(Commandes!$H$2:$H$301,Commandes!$L$2:$L$301,A11) -> 0 | G11: =SUMIFS(Commandes!$I$2:$I$301,Commandes!$L$2:$L$301,A11) -> 0 | H11: =SUMIFS(Commandes!$K$2:$K$301,Commandes!$L$2:$L$301,A11) -> 0
A12: 46600 | B12: =COUNTIFS(Commandes!$L$2:$L$301,A12) -> 0 | C12: =SUMIFS(Commandes!$E$2:$E$301,Commandes!$L$2:$L$301,A12) -> 0 | D12: =SUMIFS(Commandes!$F$2:$F$301,Commandes!$L$2:$L$301,A12) -> 0 | E12: =SUMIFS(Commandes!$G$2:$G$301,Commandes!$L$2:$L$301,A12) -> 0 | F12: =SUMIFS(Commandes!$H$2:$H$301,Commandes!$L$2:$L$301,A12) -> 0 | G12: =SUMIFS(Commandes!$I$2:$I$301,Commandes!$L$2:$L$301,A12) -> 0 | H12: =SUMIFS(Commandes!$K$2:$K$301,Commandes!$L$2:$L$301,A12) -> 0
A13: 46631 | B13: =COUNTIFS(Commandes!$L$2:$L$301,A13) -> 0 | C13: =SUMIFS(Commandes!$E$2:$E$301,Commandes!$L$2:$L$301,A13) -> 0 | D13: =SUMIFS(Commandes!$F$2:$F$301,Commandes!$L$2:$L$301,A13) -> 0 | E13: =SUMIFS(Commandes!$G$2:$G$301,Commandes!$L$2:$L$301,A13) -> 0 | F13: =SUMIFS(Commandes!$H$2:$H$301,Commandes!$L$2:$L$301,A13) -> 0 | G13: =SUMIFS(Commandes!$I$2:$I$301,Commandes!$L$2:$L$301,A13) -> 0 | H13: =SUMIFS(Commandes!$K$2:$K$301,Commandes!$L$2:$L$301,A13) -> 0
... A16: 46722 | B16: =COUNTIFS(Commandes!$L$2:$L$301,A16) -> 0 | C16: =SUMIFS(Commandes!$E$2:$E$301,Commandes!$L$2:$L$301,A16) -> 0 | D16: =SUMIFS(Commandes!$F$2:$F$301,Commandes!$L$2:$L$301,A16) -> 0 | E16: =SUMIFS(Commandes!$G$2:$G$301,Commandes!$L$2:$L$301,A16) -> 0 | F16: =SUMIFS(Commandes!$H$2:$H$301,Commandes!$L$2:$L$301,A16) -> 0 | G16: =SUMIFS(Commandes!$I$2:$I$301,Commandes!$L$2:$L$301,A16) -> 0 | H16: =SUMIFS(Commandes!$K$2:$K$301,Commandes!$L$2:$L$301,A16) -> 0
A17: TOTAL | B17: =SUM(B2:B16) -> 1 | C17: =SUM(C2:C16) -> 29.99 | D17: =SUM(D2:D16) -> 18.4 | E17: =SUM(E2:E16) -> 0.7 | F17: =SUM(F2:F16) -> 3.69 | G17: =SUM(G2:G16) -> 0 | H17: =SUM(H2:H16) -> 7.2
A19: La colonne « CA à déclarer URSSAF » = ce que tu déclares chaque mois (ou chaque trimestre : additionne les 3 mois).
